justbuild/__init__.py
justbuild/__main__.py
justbuild/cli.py
justbuild/config.py
justbuild/lfg_cli.py
justbuild/ui.py
justbuild/codediff/__init__.py
justbuild/codediff/features.py
justbuild/codediff/git_diff_calculations.py
justbuild/codediff/git_wrappers.py
justbuild/codediff/human_in_the_loop.py
justbuild/codediff/merging.py
justbuild/codediff/models.py
justbuild/codediff/models_llm.py
tests/__init__.py
tests/all.py
tests/test_cli.py
tests/test_config.py
tests/test_install.py
justbuild-0.3.2.dist-info/LICENSE
justbuild-0.3.2.dist-info/METADATA
justbuild-0.3.2.dist-info/WHEEL
justbuild-0.3.2.dist-info/entry_points.txt
justbuild-0.3.2.dist-info/top_level.txt
justbuild-0.3.2.dist-info/RECORD
