Metadata-Version: 2.1
Name: justbuild
Version: 0.3.2
Summary: 🚀 LFG! 💬 Chat Assisted Programming Tools to JustBuild it 💻
Home-page: https://github.com/closedloop-technologies/letsgo-sh
Author: Sean Kruzel @ Closedloop Technologies
Author-email: sean@closedloop.lech
Classifier: Development Status :: 3 - Alpha
Classifier: Intended Audience :: Developers
Classifier: License :: OSI Approved :: MIT License
Classifier: Operating System :: OS Independent
Classifier: Programming Language :: Python :: 3
Classifier: Programming Language :: Python :: 3.7
Classifier: Programming Language :: Python :: 3.8
Classifier: Programming Language :: Python :: 3.9
Classifier: Programming Language :: Python :: 3.10
Classifier: Programming Language :: Python :: 3.11
Classifier: Programming Language :: Python :: 3.12
Classifier: Programming Language :: Python :: 3.13
Requires-Python: >=3.7
License-File: LICENSE
